[
    {
        "name": "Novo Echo Spot com Alexa",
        "price": "R$ 449.00",
        "image": "https://m.media-amazon.com/images/I/71+RI03uZvL._AC_SY300_SX300_.jpg",
        "link": "https://www.amazon.com.br/echo-spot-despertador-inteligente-com-alexa-cor-preta/dp/B0C2RS4ZG6?ref=dlx_deals_dg_dcl_B0C2RS4ZG6_dt_sl14_53"
    },
    {
        "name": "Bicicleta Aro 29 Caloi Velox MY23",
        "price": "R$ 734.90",
        "image": "https://m.media-amazon.com/images/I/71jjmLY5WtL._AC_SX425_.jpg",
        "link": "https://www.amazon.com.br/Bicicleta-Caloi-Velox-Preta-MY23/dp/B0BZQG5CMB?ref=dlx_deals_dg_dcl_B0BZQG5CMB_dt_sl14_53"
    },
    {
        "name": "Neve Papel Higiênico Toque de Seda Folha Dupla",
        "price": "R$ 43.90",
        "image": "https://m.media-amazon.com/images/I/61b0uNN8kQL._AC_SX425_.jpg",
        "link": "https://www.amazon.com.br/Papel-Higi%C3%AAnico-Neve-Toque-rolos/dp/B07FSVKWDC?ref=dlx_deals_dg_dcl_B07FSVKWDC_dt_sl14_53"
    },
    {
        "name": "Zoetis Simparic 20Mg 5 1 Até 10Kg 03 Compr Para Cães",
        "price": "R$ 151.91",
        "image": "https://m.media-amazon.com/images/I/61pZi4gGriL._AC_SX425_.jpg",
        "link": "https://www.amazon.com.br/Simparic-20mg-10kg-Compr-Zoetis/dp/B07Y1Y7NDX?ref=dlx_deals_dg_dcl_B07Y1Y7NDX_dt_sl14_53"
    }
]